LICENSE
MANIFEST.in
README.md
quicktest.py
settings_test.py
setup.py
django_email_html.egg-info/PKG-INFO
django_email_html.egg-info/SOURCES.txt
django_email_html.egg-info/dependency_links.txt
django_email_html.egg-info/not-zip-safe
django_email_html.egg-info/pbr.json
django_email_html.egg-info/requires.txt
django_email_html.egg-info/top_level.txt
email_html/__init__.py
email_html/__init__.pyc
email_html/mail.py
email_html/mail.pyc
email_html/models.py
email_html/models.pyc
email_html/templatetags/__init__.py
email_html/templatetags/__init__.pyc
email_html/templatetags/email_html.py
email_html/templatetags/email_html.pyc