Metadata-Version: 1.1
Name: django-email-html
Version: 0.2.0
Summary: Application for switching from Django plain-text emails to html emails with 2 bodies: html and plain-text, generated automatically from html
Home-page: https://github.com/ramusus/django-email-html
Author: ramusus
Author-email: ramusus@gmail.com
License: BSD
Download-URL: http://pypi.python.org/pypi/django-email-html
Platform: UNKNOWN
Classifier: Development Status :: 4 - Beta
Classifier: Environment :: Web Environment
Classifier: Intended Audience :: Developers
Classifier: License :: OSI Approved :: BSD License
Classifier: Operating System :: OS Independent
Classifier: Programming Language :: Python
Classifier: Topic :: Software Development :: Libraries :: Python Modules
